README.md
setup.py
airplay/__init__.py
airplay/airplay.py
airplay/cli.py
airplay/http_server.py
airplay/tests.py
airplay.egg-info/PKG-INFO
airplay.egg-info/SOURCES.txt
airplay.egg-info/dependency_links.txt
airplay.egg-info/entry_points.txt
airplay.egg-info/requires.txt
airplay.egg-info/top_level.txt
airplay/vendor/__init__.py
airplay/vendor/httpheader.py