Metadata-Version: 1.1
Name: airplay
Version: 0.0.5
Summary: A python client for AirPlay video
Home-page: https://github.com/cnelson/python-airplay
Author: Chris Nelson
Author-email: cnelson@cnelson.org
License: Public Domain
Keywords: airplay appletv
Platform: UNKNOWN
Classifier: Development Status :: 3 - Alpha
Classifier: Intended Audience :: Developers
Classifier: License :: Public Domain
Classifier: Programming Language :: Python :: 2
Classifier: Programming Language :: Python :: 2.7
Classifier: Programming Language :: Python :: 3
